ocrpy/__init__.py
ocrpy/experimental/__init__.py
ocrpy/experimental/document_classifier.py
ocrpy/experimental/layout_parser.py
ocrpy/io/__init__.py
ocrpy/io/reader.py
ocrpy/io/writer.py
ocrpy/parsers/__init__.py
ocrpy/parsers/core.py
ocrpy/parsers/table/__init__.py
ocrpy/parsers/table/aws_table.py
ocrpy/parsers/table/table_parser.py
ocrpy/parsers/text/__init__.py
ocrpy/parsers/text/aws_text.py
ocrpy/parsers/text/gcp_text.py
ocrpy/parsers/text/tesseract_text.py
ocrpy/parsers/text/text_parser.py
ocrpy/pipelines/__init__.py
ocrpy/pipelines/config.py
ocrpy/pipelines/index_pipeline.py
ocrpy/pipelines/text_pipeline.py
ocrpy/utils/__init__.py
ocrpy/utils/exceptions.py
ocrpy/utils/logger.py
ocrpy/utils/utils.py
ocrpy-0.3.10.dist-info/METADATA
ocrpy-0.3.10.dist-info/WHEEL
ocrpy-0.3.10.dist-info/licenses/AUTHORS.rst
ocrpy-0.3.10.dist-info/licenses/LICENSE
ocrpy-0.3.10.dist-info/RECORD
