Metadata-Version: 2.1
Name: ocrpy
Version: 0.3.10
Summary: unified interface to google vision, aws textract, azure & tesseract OCR tools.
Project-URL: Source, https://github.com/maxent-ai/ocrpy
Author-email: Maxentlabs <info@maxentlabs.com>
License: MIT
Classifier: Development Status :: 4 - Beta
Classifier: Intended Audience :: Developers
Classifier: Intended Audience :: Education
Classifier: Intended Audience :: Financial and Insurance Industry
Classifier: Intended Audience :: Healthcare Industry
Classifier: Intended Audience :: Information Technology
Classifier: Intended Audience :: Legal Industry
Classifier: Intended Audience :: Other Audience
Classifier: Intended Audience :: Science/Research
Classifier: Intended Audience :: Telecommunications Industry
Classifier: License :: OSI Approved :: Apache Software License
Classifier: License :: OSI Approved :: MIT License
Classifier: Natural Language :: English
Classifier: Operating System :: OS Independent
Classifier: Programming Language :: Python :: 3.7
Classifier: Programming Language :: Python :: 3.8
Classifier: Topic :: Scientific/Engineering :: Artificial Intelligence
Classifier: Topic :: Scientific/Engineering :: Image Recognition
Classifier: Topic :: Scientific/Engineering :: Information Analysis
Classifier: Topic :: Software Development :: Libraries :: Python Modules
Classifier: Topic :: Text Processing :: Linguistic
Requires-Python: >=3.7
Requires-Dist: attrs==21.4.0
Requires-Dist: beautifulsoup4==4.9.1
Requires-Dist: boto3==1.19.7
Requires-Dist: cloudpathlib==0.9.0
Requires-Dist: farm-haystack==1.6.0
Requires-Dist: google-cloud-vision==1.0.0
Requires-Dist: layoutparser==0.3.4
Requires-Dist: numpy==1.21.1
Requires-Dist: opencv-python==4.1.2.30
Requires-Dist: paddlepaddle==2.1.0
Requires-Dist: pandas==1.3.3
Requires-Dist: pdf2image==1.14.0
Requires-Dist: pytesseract==0.3.6
Requires-Dist: python-dotenv==0.17.1
Requires-Dist: torchvision==0.11.3
Requires-Dist: tqdm==4.64.0
Requires-Dist: transformers==4.20.1
